Metadata-Version: 2.1
Name: tkitTranslator
Version: 0.1.2
Summary: Terry tkitTranslator 翻译
Home-page: https://www.terrychan.org/translator/
Author: Terry Chan
Author-email: napoler2008@gmail.com
License: UNKNOWN
Platform: UNKNOWN
